<?xml version="1.0" encoding="UTF-8"?>
<!--Sample XML file generated by XMLSpy v2013 rel. 2 sp2 (x64) (http://www.altova.com)-->
<tns:GetActivitiesResponse xsi:schemaLocation="urn:riv:clinicalprocess:activity:actions:GetActivitiesResponder:1 GetActivitiesResponder_1.0.xsd" xmlns:xsi="http://www.w3.org/2001/XMLSchema-instance" xmlns:core="urn:riv:clinicalprocess:activity:actions:1" xmlns:tns="urn:riv:clinicalprocess:activity:actions:GetActivitiesResponder:1">
	<tns:activityGroup>
		<core:patient>
			<core:id>
				<core:root>1.2.752.129.2.1.3.1</core:root>
				<core:extension>191212121212</core:extension>
			</core:id>
			<core:dateOfBirth>19121212</core:dateOfBirth>
			<core:gender>
				<core:code>2</core:code>
				<core:codeSystem>1.2.752.129.2.2.1.1</core:codeSystem>
				<core:displayName>Kvinna</core:displayName>
			</core:gender>
		</core:patient>
		<core:performerRole>
			<core:id>
				<core:root>1.2.752.129.2.2.1.4</core:root>
				<core:extension>SE2321000016-A19L</core:extension>
			</core:id>
			<core:code>
				<core:code>PC</core:code>
				<core:codeSystem>2.16.840.1.113883.5.111</core:codeSystem>
			</core:code>
			<core:careUnit>
				<core:id>
					<core:root>1.2.752.129.2.1.4.1</core:root>
					<core:extension>SE2321000016-1021</core:extension>
				</core:id>
				<core:name>Läkargruppen Norrmalmstorg</core:name>
				<core:careGiver>
					<core:id>
						<core:root>1.2.752.129.2.1.4.1</core:root>
						<core:extension>SE2321000016-5KV9</core:extension>
					</core:id>
				</core:careGiver>
			</core:careUnit>
		</core:performerRole>
		<core:additionalParticipant>
			<core:id>
				<core:root>1.2.752.129.2.1.4.1</core:root>
				<core:extension>SE2321000016-A21K</core:extension>
			</core:id>
			<core:type>
				<core:code>SPRF</core:code>
				<core:codeSystem>2.16.840.1.113883.5.90</core:codeSystem>
			</core:type>
			<core:role>
				<core:code>SC</core:code>
				<core:codeSystem>2.16.840.1.113883.5.111</core:codeSystem>
			</core:role>

		</core:additionalParticipant>
		<core:sourceSystem>
			<core:id>
				<core:root>1.2.752.129.2.1.4.1</core:root>
				<core:extension>SE123SourceSys456</core:extension>
			</core:id>
		</core:sourceSystem>
		<core:location>
			<core:id>
				<core:root>1.2.752.129.2.1.4.1</core:root>
				<core:extension>SE2321000016-1021</core:extension>
			</core:id>
			<core:name>Invärtesmedicin, Läkargruppen Norrmalmstorg</core:name>
			<core:address>
				<core:part>
					<core:value>Norrlandsgatan 11</core:value>
					<core:type>SAL</core:type>
				</core:part>
				<core:part>
					<core:value>111 47</core:value>
					<core:type>ZIP</core:type>
				</core:part>
				<core:part>
					<core:value>Stockholm</core:value>
					<core:type>CTY</core:type>
				</core:part>
				<core:part>
					<core:value>Sverige</core:value>
					<core:type>CNT</core:type>
				</core:part>
			</core:address>
			<core:electronicAddress>
				<core:use>voice</core:use>
				<core:value>08-677 00 40</core:value>
			</core:electronicAddress>
			<core:electronicAddress>
				<core:use>fax</core:use>
				<core:value>08-677 00 60</core:value>
			</core:electronicAddress>
		</core:location>
		<core:activity>
			<core:id>
				<core:root>1.2.752.129.2.1.4.1</core:root>
				<core:extension>SE2321000016-35D9:123456789</core:extension>
			</core:id>
			<core:code>
				<core:code>24443003</core:code>
				<core:codeSystem>1.2.752.116.2.1.1</core:codeSystem>
				<core:codeSystemName>SNOMED CT SE</core:codeSystemName>
				<core:displayName>total tyreoidektomi</core:displayName>
			</core:code>
			<core:time>
				<core:start>
					<core:format>YYYYMMDDhhmmss</core:format>
					<core:value>20131006110000</core:value>
				</core:start>
			</core:time>
			<core:description>Hela sköldkörteln har tagits bort</core:description>
			<core:approvedForPatient>false</core:approvedForPatient>
			<core:registrationTime>20131006110000</core:registrationTime>
			<core:relation>
				<core:code>
					<core:code>47429007</core:code>
					<core:codeSystem>1.2.752.116.2.1.1</core:codeSystem>
					<core:displayName>associerad med</core:displayName>
				</core:code>
				<core:referredInformation>
					<core:id>
						<core:root>1.2.752.129.2.1.4.1</core:root>
						<core:extension>SE2321000016-35DG</core:extension>
					</core:id>
					<core:time>
						<core:format>YYYYMMDDhhmmss</core:format>
						<core:value>20131007121500</core:value>
					</core:time>
					<core:type>urn:riv:clinicalprocess:healthcond:basic:GetObservation</core:type>
					<core:informationOwner>
						<core:id>
							<core:root>1.2.752.129.2.1.4.1</core:root>
							<core:extension>SE2321000016-35DG</core:extension>
						</core:id>
					</core:informationOwner>
				</core:referredInformation>
			</core:relation>
		</core:activity>
	</tns:activityGroup>
</tns:GetActivitiesResponse>